ifscSearch/__init__.py
ifscSearch/ifsc_search.py
ifscSearch-1.0.4.1.dist-info/METADATA
ifscSearch-1.0.4.1.dist-info/WHEEL
ifscSearch-1.0.4.1.dist-info/top_level.txt
ifscSearch-1.0.4.1.dist-info/RECORD
