Metadata-Version: 2.1
Name: ifscSearch
Version: 1.0.4.1
Summary: A module to search IFSC codes.
Home-page: https://github.com/panditamey/ifscSearch
Author: Amey Pandit
Classifier: Programming Language :: Python :: 3
Classifier: License :: OSI Approved :: MIT License
Requires-Dist: requests
